{
  "Workflows": [
    {
      "Path": null,
      "SortBy": 0,
      "VariablesSectionElementsOrder": [],
      "ArgumentsSectionElementsOrder": null,
      "ConstantsSectionElementsOrder": [],
      "AddedNamespaces": null
    },
    {
      "Path": "Main.xaml",
      "SortBy": 0,
      "VariablesSectionElementsOrder": [
        "varTenant&StateMachine_1",
        "varAppID&StateMachine_1",
        "varSenha&StateMachine_1",
        "varUser&StateMachine_1",
        "TransactionItem&StateMachine_1",
        "SystemException&StateMachine_1",
        "BusinessException&StateMachine_1",
        "TransactionNumber&StateMachine_1",
        "Config&StateMachine_1",
        "RetryNumber&StateMachine_1",
        "TransactionField2&StateMachine_1",
        "TransactionField1&StateMachine_1",
        "TransactionID&StateMachine_1",
        "dt_TransactionData&StateMachine_1",
        "ConsecutiveSystemExceptions&StateMachine_1",
        "FFmpegProcess&StateMachine_1",
        "BigQueryDatabaseConnection&StateMachine_1",
        "ShouldStop&Sequence_25"
      ],
      "ArgumentsSectionElementsOrder": [
        "in_OrchestratorQueueName",
        "in_OrchestratorQueueFolder",
        "in_MaxDurationVideoRecorder"
      ],
      "ConstantsSectionElementsOrder": [],
      "AddedNamespaces": null
    },
    {
      "Path": "ProcessBox/AUTENTICACOES/CredenciaisGoogle.xaml",
      "SortBy": 0,
      "VariablesSectionElementsOrder": [],
      "ArgumentsSectionElementsOrder": [
        "in_Config",
        "out_BigQueryDatabaseConnection"
      ],
      "ConstantsSectionElementsOrder": [],
      "AddedNamespaces": null
    },
    {
      "Path": "Framework/StartStopScreenRecorder.xaml",
      "SortBy": 0,
      "VariablesSectionElementsOrder": [
        "RecorderProcessName&Sequence_1",
        "RecordingFilePath&Sequence_14",
        "RecorderResolution&Sequence_14"
      ],
      "ArgumentsSectionElementsOrder": [
        "in_OrchestratorQueueName",
        "in_OrchestratorQueueFolder",
        "in_MaxDurationVideoRecorder"
      ],
      "ConstantsSectionElementsOrder": [],
      "AddedNamespaces": null
    },
    {
      "Path": "ProcessBox/AUTENTICACOES/CredenciaisOfficeAzure.xaml",
      "SortBy": 0,
      "VariablesSectionElementsOrder": [],
      "ArgumentsSectionElementsOrder": [
        "in_Config",
        "out_user",
        "out_senha"
      ],
      "ConstantsSectionElementsOrder": [],
      "AddedNamespaces": null
    },
    {
      "Path": "Framework/InitAllSettings.xaml",
      "SortBy": 0,
      "VariablesSectionElementsOrder": [
        "dt_SettingsAndConstants&Sequence_5",
        "dt_Assets&Sequence_6",
        "AssetValue&Sequence_11"
      ],
      "ArgumentsSectionElementsOrder": [
        "in_ConfigFile",
        "in_ConfigSheets",
        "out_Config"
      ],
      "ConstantsSectionElementsOrder": [],
      "AddedNamespaces": null
    },
    {
      "Path": "Framework/GetTransactionData.xaml",
      "SortBy": 0,
      "VariablesSectionElementsOrder": [],
      "ArgumentsSectionElementsOrder": [
        "in_TransactionNumber",
        "in_Config",
        "out_TransactionItem",
        "out_TransactionField1",
        "out_TransactionField2",
        "out_TransactionID",
        "io_dt_TransactionData"
      ],
      "ConstantsSectionElementsOrder": [],
      "AddedNamespaces": null
    },
    {
      "Path": "Framework/Process.xaml",
      "SortBy": 0,
      "VariablesSectionElementsOrder": [
        "str_caminho_json&Sequence_1",
        "dict_fatura_fields&Sequence_1",
        "list_dict_fatura_table&Sequence_1",
        "varPath&Sequence_1",
        "varBname&Sequence_5",
        "jsonObj_fatura&Sequence_3",
        "dict_Item&Sequence_3",
        "json_str&Sequence_3"
      ],
      "ArgumentsSectionElementsOrder": [
        "in_varAppID",
        "in_varTenant",
        "in_varSenha",
        "in_varUser",
        "in_TransactionItem",
        "in_Config"
      ],
      "ConstantsSectionElementsOrder": [],
      "AddedNamespaces": null
    },
    {
      "Path": "ProcessBox/Office/SalvaPDF.xaml",
      "SortBy": 0,
      "VariablesSectionElementsOrder": [
        "str_caminho_fatura&Flowchart_1",
        "varBname&Sequence_1",
        "varPath&Sequence_1"
      ],
      "ArgumentsSectionElementsOrder": [
        "in_varSenha",
        "in_varTenant",
        "in_varAppID",
        "in_varUser",
        "in_dict_fatura_fields",
        "in_Config",
        "in_TransactionItem"
      ],
      "ConstantsSectionElementsOrder": [],
      "AddedNamespaces": null
    },
    {
      "Path": "Framework/InitAllApplications.xaml",
      "SortBy": 0,
      "VariablesSectionElementsOrder": [],
      "ArgumentsSectionElementsOrder": [
        "in_Config"
      ],
      "ConstantsSectionElementsOrder": [],
      "AddedNamespaces": null
    },
    {
      "Path": "Framework/SetTransactionStatus.xaml",
      "SortBy": 0,
      "VariablesSectionElementsOrder": [
        "QueueRetry&Sequence_17",
        "ScreenshotPath&Sequence_17"
      ],
      "ArgumentsSectionElementsOrder": [
        "in_BusinessException",
        "in_TransactionField1",
        "in_TransactionField2",
        "in_TransactionID",
        "in_SystemException",
        "in_Config",
        "in_TransactionItem",
        "io_RetryNumber",
        "io_TransactionNumber",
        "io_ConsecutiveSystemExceptions"
      ],
      "ConstantsSectionElementsOrder": [],
      "AddedNamespaces": null
    },
    {
      "Path": "Framework/CloseAllApplications.xaml",
      "SortBy": 0,
      "VariablesSectionElementsOrder": [
        "TransactionItem&StateMachine_1",
        "SystemException&StateMachine_1",
        "BusinessException&StateMachine_1",
        "TransactionNumber&StateMachine_1",
        "Config&StateMachine_1",
        "RetryNumber&StateMachine_1",
        "TransactionField2&StateMachine_1",
        "TransactionField1&StateMachine_1",
        "TransactionID&StateMachine_1",
        "dt_TransactionData&StateMachine_1",
        "ConsecutiveSystemExceptions&StateMachine_1",
        "FFmpegProcess&StateMachine_1",
        "BigQueryDatabaseConnection&StateMachine_1",
        "varUser&Sequence_40",
        "varSenha&Sequence_40",
        "varAppID&Sequence_40",
        "varTenant&Sequence_40",
        "ShouldStop&Sequence_25"
      ],
      "ArgumentsSectionElementsOrder": [
        "in_TransactionNumber",
        "in_Config",
        "out_TransactionItem",
        "out_TransactionField1",
        "out_TransactionField2",
        "out_TransactionID",
        "io_dt_TransactionData"
      ],
      "ConstantsSectionElementsOrder": [],
      "AddedNamespaces": null
    },
    {
      "Path": "DeserializeJson.xaml",
      "SortBy": 0,
      "VariablesSectionElementsOrder": [
        "JsonText&Sequence_1",
        "JsonObj&Sequence_1",
        "Age&Sequence_1"
      ],
      "ArgumentsSectionElementsOrder": [],
      "ConstantsSectionElementsOrder": [],
      "AddedNamespaces": null
    },
    {
      "Path": "jsontexte.xaml",
      "SortBy": 0,
      "VariablesSectionElementsOrder": [
        "dictItem&Sequence_1",
        "VARDICTABLE&Sequence_1",
        "vardict&Sequence_1",
        "JsonObject&Sequence_1",
        "jsontxt&Sequence_1"
      ],
      "ArgumentsSectionElementsOrder": [],
      "ConstantsSectionElementsOrder": [],
      "AddedNamespaces": null
    },
    {
      "Path": "DeserializeJson/DeserializeJson.xaml",
      "SortBy": 0,
      "VariablesSectionElementsOrder": [
        "JsonText&Sequence_1",
        "JsonObj&Sequence_1",
        "Age&Sequence_1"
      ],
      "ArgumentsSectionElementsOrder": [],
      "ConstantsSectionElementsOrder": [],
      "AddedNamespaces": null
    }
  ]
}